mft-0.6.1.dist-info/METADATA
mft-0.6.1.dist-info/WHEEL
mft/__init__.py
mft/mft.pyd
mft-0.6.1.dist-info/RECORD
