Metadata-Version: 2.1
Name: mft
Version: 0.6.1
Classifier: Development Status :: 3 - Alpha
Classifier: Intended Audience :: Developers
Classifier: License :: OSI Approved :: MIT License
Classifier: Operating System :: MacOS :: MacOS X
Classifier: Operating System :: POSIX
Classifier: Programming Language :: Python :: Implementation :: CPython
Classifier: Programming Language :: Python :: Implementation :: PyPy
Classifier: Programming Language :: Python
Classifier: Programming Language :: Rust
Requires-Dist: pytest; extra == 'test'
Provides-Extra: test
Author: Omer Ben-Amram <omerbenamram@gmail.com>
Author-email: Omer Ben-Amram <omerbenamram@gmail.com>
Requires-Python: >=3.7
